{
  "gitSyncId": "683939ae8c263668834b8feb_7827ab60-ff06-461c-866d-630a3d8e853d",
  "id": "Widgets_Total_record_movies1",
  "pluginId": "mongo-plugin",
  "pluginType": "DB",
  "unpublishedAction": {
    "actionConfiguration": {
      "encodeParamsToggle": true,
      "formData": {
        "aggregate": {
          "limit": {
            "data": "10"
          }
        },
        "body": {
          "data": "{\n  \"find\": \"movies\",\n  \"filter\": {\n    \"homepage\": \"https://movies.disney.com/cruella\"\n  },\n  \"sort\": {\n    \"_id\": 1\n  },\n  \"limit\": 10\n}\n"
        },
        "collection": {
          "data": "movies"
        },
        "command": {
          "data": "COUNT"
        },
        "count": {
          "query": {
            "data": ""
          }
        },
        "delete": {
          "limit": {
            "data": "SINGLE"
          }
        },
        "find": {
          "limit": {
            "data": "10"
          },
          "query": {
            "data": "{ \"homepage\": \"https://movies.disney.com/cruella\"}"
          },
          "sort": {
            "data": "{\"_id\": 1}"
          }
        },
        "smartSubstitution": {
          "data": true
        },
        "updateMany": {
          "limit": {
            "data": "SINGLE"
          }
        }
      },
      "paginationType": "NONE",
      "timeoutInMillisecond": 10000
    },
    "confirmBeforeExecute": false,
    "datasource": {
      "id": "Movies",
      "isAutoGenerated": false,
      "name": "Movies",
      "pluginId": "mongo-plugin"
    },
    "dynamicBindingPathList": [
      {
        "key": "formData.count.query.data"
      }
    ],
    "name": "Total_record_movies1",
    "pageId": "Widgets",
    "runBehaviour": "ON_PAGE_LOAD",
    "userSetOnLoad": false
  }
}